.gitignore
CHANGES.rst
DESCRIPTION.rst
LICENSE
MANIFEST.in
README.md
RELEASE.md
requirements.txt
setup.py
doc/Makefile
doc/make.bat
doc/source/conf.py
doc/source/examples.rst
doc/source/index.rst
doc/source/install.rst
doc/source/modules.rst
doc/source/sklweka.rst
doc/source/_static/logo.jpg
doc/source/_static/logo.pdf
doc/source/_static/logo.png
doc/source/_static/logo.svg
src/sklearn_weka_plugin.egg-info/PKG-INFO
src/sklearn_weka_plugin.egg-info/SOURCES.txt
src/sklearn_weka_plugin.egg-info/dependency_links.txt
src/sklearn_weka_plugin.egg-info/requires.txt
src/sklearn_weka_plugin.egg-info/top_level.txt
src/sklweka/__init__.py
src/sklweka/classifiers.py
src/sklweka/clusters.py
src/sklweka/datagenerators.py
src/sklweka/dataset.py
src/sklweka/jvm.py
src/sklweka/packages.py
src/sklweka/preprocessing.py