Metadata-Version: 2.1
Name: sklearn-weka-plugin
Version: 0.0.8
Summary: Library for making Weka algorithms available within scikit-learn. Relies on the python-weka-wrapper3 library.
Home-page: https://github.com/fracpete/sklearn-weka-plugin
Author: Peter "fracpete" Reutemann
Author-email: sklweka@fracpete.org
License: GNU General Public License version 3.0 (GPLv3)
Platform: UNKNOWN
Classifier: Development Status :: 4 - Beta
Classifier: License :: OSI Approved :: GNU General Public License (GPL)
Classifier: Topic :: Scientific/Engineering :: Artificial Intelligence
Classifier: Programming Language :: Python :: 3
License-File: LICENSE
